globestylizer_kirkan95/__init__.py
globestylizer_kirkan95/abbr.py
globestylizer_kirkan95/main.py
globestylizer_kirkan95-0.1.7.dist-info/METADATA
globestylizer_kirkan95-0.1.7.dist-info/WHEEL
globestylizer_kirkan95-0.1.7.dist-info/licenses/LICENSE
globestylizer_kirkan95-0.1.7.dist-info/RECORD
