Metadata-Version: 2.1
Name: globestylizer_kirkan95
Version: 0.1.7
Summary: A tool for the Boston Globe for data cleaning
Project-URL: Homepage, https://github.com/BostonGlobe/nr-globestylizer
Author-email: Kirkland An <kirkan95@gmail.com>
License-File: LICENSE
Classifier: License :: OSI Approved :: MIT License
Classifier: Operating System :: OS Independent
Classifier: Programming Language :: Python :: 3
Requires-Python: >=3.7
